[
    {
        "idx": "CMtMedQA-49790",
        "id": "x1128",
        "cate1": "皮肤科",
        "cate2": "艾滋病",
        "conversations": [
            {
                "from": "human",
                "value": "我最近做了一个艾滋病检测，结果显示三个月前的检测结果是阴性，这是什么意思？",
                "speech": "../dataset/SpeechMedDataset/wav/CMtMedQA-49790-0.wav"
            },
            {
                "from": "assistant",
                "value": "三个月前的检测结果是阴性，说明那时候你还没被感染。艾滋病有个窗口期，在这期间可能检测不到病毒，但三个月后没查到，基本就没问题了。"
            },
            {
                "from": "human",
                "value": "那窗口期是怎么回事？为什么要有一个这样的窗口期？",
                "speech": "../dataset/SpeechMedDataset/wav/CMtMedQA-49790-2.wav"
            },
            {
                "from": "assistant",
                "value": "窗口期就是从感染到能检测出抗体的时间，一般两到六周。这段时间里抗体还没达到能被检测出来的量，所以得过段时间再测。"
            },
            {
                "from": "human",
                "value": "明白了，如果我感染了艾滋病，应该怎么办？",
                "speech": "../dataset/SpeechMedDataset/wav/CMtMedQA-49790-4.wav"
            },
            {
                "from": "assistant",
                "value": "如果感染了，就要赶紧去医院接受治疗，按医嘱吃药，还要注意别传染给别人，比如用安全套、不要共用针头这些。"
            },
            {
                "from": "human",
                "value": "好的，谢谢你的回答。",
                "speech": "../dataset/SpeechMedDataset/wav/CMtMedQA-49790-6.wav"
            },
            {
                "from": "assistant",
                "value": "不用谢，有问题随时问。"
            }
        ],
        "gender": "未知",
        "age": "未知",
        "syn_model": "FishSpeech"
    },
    {
        "idx": "CMtMedQA-49791",
        "id": "x1129",
        "cate1": "外科",
        "cate2": "男科",
        "conversations": [
            {
                "from": "human",
                "value": "我发现自己的精子透明无色，这正常吗？",
                "speech": "../dataset/SpeechMedDataset/wav/CMtMedQA-49791-0.wav"
            },
            {
                "from": "assistant",
                "value": "不太正常，可能是无精症的表现，需要做些检查确认一下。"
            },
            {
                "from": "human",
                "value": "那我应该怎么做？",
                "speech": "../dataset/SpeechMedDataset/wav/CMtMedQA-49791-2.wav"
            },
            {
                "from": "assistant",
                "value": "去查个精液常规，看看是不是有炎症或者其他问题。"
            },
            {
                "from": "human",
                "value": "如果确诊了无精症，怎么治？",
                "speech": "../dataset/SpeechMedDataset/wav/CMtMedQA-49791-4.wav"
            },
            {
                "from": "assistant",
                "value": "可以试试药物治疗、手术治疗或者辅助生殖技术，具体看情况。"
            },
            {
                "from": "human",
                "value": "我应该去哪个科室？",
                "speech": "../dataset/SpeechMedDataset/wav/CMtMedQA-49791-6.wav"
            },
            {
                "from": "assistant",
                "value": "可以先去看男科，他们会根据情况推荐你去生殖医学中心。"
            },
            {
                "from": "human",
                "value": "我现在挺担心的，这会影响治疗效果吗？",
                "speech": "../dataset/SpeechMedDataset/wav/CMtMedQA-49791-8.wav"
            },
            {
                "from": "assistant",
                "value": "会有些影响，压力大的话可能会影响激素水平。尽量放松心情，积极面对吧。"
            }
        ],
        "gender": "男",
        "age": "未知",
        "syn_model": "FishSpeech"
    },
    {
        "idx": "CMtMedQA-49792",
        "id": "x1130",
        "cate1": "外科",
        "cate2": "骨科",
        "conversations": [
            {
                "from": "human",
                "value": "我屁股尾骨疼，感觉挺奇怪的，有点担心。",
                "speech": "../dataset/SpeechMedDataset/wav/CMtMedQA-49792-0.wav"
            },
            {
                "from": "assistant",
                "value": "嗯，屁股尾骨疼可能是因为肌肉拉伤或者骨折之类的。你是突然开始疼的吗？"
            },
            {
                "from": "human",
                "value": "对，大概是从前几天开始的，有时候换个姿势就会更疼。",
                "speech": "../dataset/SpeechMedDataset/wav/CMtMedQA-49792-2.wav"
            },
            {
                "from": "assistant",
                "value": "这样啊，有可能是肌肉拉伤或者是轻微的骨折。除了疼，还有别的感觉吗？比如动不了或者肿了什么的？"
            },
            {
                "from": "human",
                "value": "没有别的感觉，就是有时候会有点刺痛。",
                "speech": "../dataset/SpeechMedDataset/wav/CMtMedQA-49792-4.wav"
            },
            {
                "from": "assistant",
                "value": "那你试试用热水袋敷一敷，轻轻按摩下周围，还可以吃点活血化瘀的中药。平时多吃点蔬菜水果，少喝酒抽烟，别吃太辣的东西。"
            },
            {
                "from": "human",
                "value": "好的，那平时还有什么要注意的吗？",
                "speech": "../dataset/SpeechMedDataset/wav/CMtMedQA-49792-6.wav"
            },
            {
                "from": "assistant",
                "value": "注意休息，不要长时间坐着不动，隔一会儿起来走走。如果疼得厉害或者一直不好，最好去医院看看，拍个片子啥的确认一下。"
            }
        ],
        "gender": "未知",
        "age": "未知",
        "syn_model": "FishSpeech"
    }
]